<idea-plugin>
  <extensionPoints>
    <extensionPoint qualifiedName="icu.windea.pls.paradoxModDependenciesImporter" interface="icu.windea.pls.core.tool.importer.ParadoxModDependenciesImporter"/>
    <extensionPoint qualifiedName="icu.windea.pls.paradoxModDependenciesExporter" interface="icu.windea.pls.core.tool.exporter.ParadoxModDependenciesExporter"/>
  </extensionPoints>

  <extensions defaultExtensionNs="icu.windea.pls">
    <!--<paradoxModDependenciesImporter implementation="icu.windea.pls.core.tool.importer.ParadoxFromGameImporter"/>-->
    <!--<paradoxModDependenciesImporter implementation="icu.windea.pls.core.tool.importer.ParadoxFromLauncherImporter"/>-->
    <!--<paradoxModDependenciesImporter implementation="icu.windea.pls.core.tool.importer.ParadoxFromLauncherBetaImporter"/>-->
    <paradoxModDependenciesImporter implementation="icu.windea.pls.core.tool.importer.ParadoxFromLauncherJsonImporter"/>
    
    <paradoxModDependenciesExporter implementation="icu.windea.pls.core.tool.exporter.ParadoxToLauncherJsonExporter"/>
  </extensions>
</idea-plugin>
